odoo/addons/product_sale_tax_price_included/README.rst
odoo/addons/product_sale_tax_price_included/__init__.py
odoo/addons/product_sale_tax_price_included/__manifest__.py
odoo/addons/product_sale_tax_price_included/demo/account_tax.xml
odoo/addons/product_sale_tax_price_included/demo/product_template.xml
odoo/addons/product_sale_tax_price_included/i18n/fr.po
odoo/addons/product_sale_tax_price_included/i18n/it.po
odoo/addons/product_sale_tax_price_included/i18n/product_sale_tax_price_included.pot
odoo/addons/product_sale_tax_price_included/models/__init__.py
odoo/addons/product_sale_tax_price_included/models/product_template.py
odoo/addons/product_sale_tax_price_included/readme/CONTRIBUTORS.rst
odoo/addons/product_sale_tax_price_included/readme/DESCRIPTION.rst
odoo/addons/product_sale_tax_price_included/static/description/icon.png
odoo/addons/product_sale_tax_price_included/static/description/index.html
odoo/addons/product_sale_tax_price_included/static/description/product_not_tax.png
odoo/addons/product_sale_tax_price_included/static/description/product_tax_excluded.png
odoo/addons/product_sale_tax_price_included/static/description/product_tax_included.png
odoo/addons/product_sale_tax_price_included/static/description/product_tax_included_and_not.png
odoo/addons/product_sale_tax_price_included/static/description/taxes_creation.png
odoo/addons/product_sale_tax_price_included/tests/__init__.py
odoo/addons/product_sale_tax_price_included/tests/test_module.py
odoo/addons/product_sale_tax_price_included/views/product_template.xml
odoo12_addon_product_sale_tax_price_included-12.0.1.0.0.99.dev6.dist-info/METADATA
odoo12_addon_product_sale_tax_price_included-12.0.1.0.0.99.dev6.dist-info/WHEEL
odoo12_addon_product_sale_tax_price_included-12.0.1.0.0.99.dev6.dist-info/top_level.txt
odoo12_addon_product_sale_tax_price_included-12.0.1.0.0.99.dev6.dist-info/RECORD
